median_polish/__init__.py
median_polish/main.py
median_polish/test/__init__.py
median_polish/test/test_main.py
median_polish-0.1.0.dist-info/METADATA
median_polish-0.1.0.dist-info/WHEEL
median_polish-0.1.0.dist-info/licenses/LICENSE.txt
median_polish-0.1.0.dist-info/RECORD
