Metadata-Version: 2.1
Name: median-polish
Version: 0.1.0
Summary: perform median polish on data
Author-email: Keji Li <mail@keji.li>
License-File: LICENSE.txt
Requires-Dist: numpy
